dictutils/__init__.py
dictutils/attr.py
dictutils/ordered_attr.py
py_dictutils-0.1.4.dist-info/LICENSE.txt
py_dictutils-0.1.4.dist-info/METADATA
py_dictutils-0.1.4.dist-info/WHEEL
py_dictutils-0.1.4.dist-info/top_level.txt
py_dictutils-0.1.4.dist-info/RECORD
