Metadata-Version: 2.1
Name: py-dictutils
Version: 0.1.4
Summary: dictionary utils
Home-page: https://github.com/hbasria/py-dictutils
Author: Hasan Basri
Author-email: ates@basri.me
License: MIT
Keywords: AttrDict OrderedAttrDict
Platform: UNKNOWN
Classifier: Development Status :: 4 - Beta
Classifier: Intended Audience :: Developers
Classifier: License :: OSI Approved :: MIT License
Classifier: Programming Language :: Python
Classifier: Programming Language :: Python :: 2
Classifier: Programming Language :: Python :: 2.7
Classifier: Programming Language :: Python :: 3
Classifier: Programming Language :: Python :: 3.3
Classifier: Programming Language :: Python :: 3.4
Classifier: Topic :: Software Development
Classifier: Topic :: Software Development :: Libraries :: Python Modules
